profinder/__init__.py
profinder/example_data.py
profinder/profinder.py
profinder-0.2.4.dist-info/METADATA
profinder-0.2.4.dist-info/WHEEL
profinder-0.2.4.dist-info/licenses/LICENSE
profinder-0.2.4.dist-info/RECORD
