Metadata-Version: 2.4
Name: profinder
Version: 0.2.4
Summary: Functions to find profiles in ocean pressure data
Project-URL: Homepage, https://oceancascades.github.io/profinder/
Project-URL: source-code, https://github.com/oceancascades/profinder
Author-email: Jesse Cusack <jesse.cusack@oregonstate.edu>
License-Expression: GPL-3.0-or-later
License-File: LICENSE
Classifier: Operating System :: OS Independent
Classifier: Programming Language :: Python :: 3
Requires-Python: >=3.11
Requires-Dist: numpy>=2.3.2
Requires-Dist: scipy>=1.16.1
